LICENSE
README.md
setup.py
stb_amount/__init__.py
stb_amount/stb.py
stb_amount.egg-info/PKG-INFO
stb_amount.egg-info/SOURCES.txt
stb_amount.egg-info/dependency_links.txt
stb_amount.egg-info/top_level.txt